[
  {
    "id": "azure_cloud_breathing",
    "name": "Azure Cloud Breathing Method",
    "category": "cultivation",
    "realmRequirement": "Mortal",
    "description": "A foundational breathing art taught to new disciples of the Azure Cloud Sect.",
    "icon": "/assets/items/book_manual.png",
    "maxLevel": 5,
    "effectsPerLevel": {
      "maxQi": 5
    }
  },
  {
    "id": "pine_shadow_step",
    "name": "Pine Shadow Step",
    "category": "movement",
    "realmRequirement": "Mortal",
    "description": "A basic footwork technique that teaches the body to move like wind through mountain pines.",
    "icon": "/assets/items/book_manual.png",
    "maxLevel": 3,
    "effectsPerLevel": {
      "physique": 1
    }
  }
]
